LICENSE
README.md
setup.py
Temperatur_Nu.egg-info/PKG-INFO
Temperatur_Nu.egg-info/SOURCES.txt
Temperatur_Nu.egg-info/dependency_links.txt
Temperatur_Nu.egg-info/requires.txt
Temperatur_Nu.egg-info/top_level.txt
temperaturnu/__init__.py
temperaturnu/temperaturnu.py