Metadata-Version: 2.1
Name: Temperatur_Nu
Version: 0.0.3
Summary: Get and or publish temperatures to temperatur.nu
Home-page: https://github.com/popeen/PyPi-Temperatur_Nu
Author: Patrik Johansson
Author-email: github@popeen.com
Classifier: Programming Language :: Python :: 3
Classifier: License :: OSI Approved :: MIT License
Classifier: Operating System :: OS Independent
Requires-Python: >=3.6
License-File: LICENSE
Requires-Dist: requests
